pytorch_lit/__init__.py
pytorch_lit/export.py
pytorch_lit/inference.py
pytorch_lit/memory.py
pytorch_lit/partial_loader.py
pytorch_lit/shared_params.py
pytorch_lit/util.py
pytorch_lit/weights.py
test/__init__.py
test/test_partial_load.py
pytorch_lit-0.1.7.dist-info/LICENSE
pytorch_lit-0.1.7.dist-info/METADATA
pytorch_lit-0.1.7.dist-info/WHEEL
pytorch_lit-0.1.7.dist-info/top_level.txt
pytorch_lit-0.1.7.dist-info/RECORD
